{
  "PLH - Activity - Teen - Active - What is new": {
    "Content": {
      "Set of messages 1": {
        "Message": "What’s new?\n•\tThink of a new skill you could learn together with your teen. For example, keeping a ball in the air or your foot, juggling, learning a new language, or playing an instrument?\n•\tTake turns in trying the new skill out.\n•\tMake sure to praise each other, and try to learn and play together!"
      }
    },
    "Technical information": {
      "Id": "c60e37aa-13fb-4d19-87cc-6a93544b1418",
      "Template_type": "1"
    }
  }
}